tai/__init__.py
tai/cli.py
tai/commands/__init__.py
tai/commands/patterns.py
tai/config/__init__.py
tai/config/settings.py
tai/config/setup.py
tai/core/__init__.py
tai/core/ai_interpreter.py
tai/core/executor.py
tai/core/interpreter.py
tai/core/os_detector.py
tai/core/terra_command.py
tai/utils/__init__.py
tai/utils/helpers.py
tai/utils/logging.py
terra_tai-0.1.0.dist-info/licenses/LICENSE
terra_tai-0.1.0.dist-info/METADATA
terra_tai-0.1.0.dist-info/WHEEL
terra_tai-0.1.0.dist-info/entry_points.txt
terra_tai-0.1.0.dist-info/top_level.txt
terra_tai-0.1.0.dist-info/RECORD
