Metadata-Version: 2.4
Name: terra-tai
Version: 0.1.0
Summary: Terra Command AI - A natural language shell command tool with AI
Home-page: https://github.com/terra-agi/terra-commands
Author: Terra AGI
Author-email: Terra AGI <contact@terra-agi.com>
Maintainer-email: Terra AGI <contact@terra-agi.com>
License: MIT
Project-URL: Homepage, https://github.com/terra-agi/terra-commands
Project-URL: Repository, https://github.com/terra-agi/terra-commands
Project-URL: Issues, https://github.com/terra-agi/terra-commands/issues
Project-URL: Changelog, https://github.com/terra-agi/terra-commands/blob/main/CHANGELOG.md
Keywords: cli,shell,command,natural-language,terminal,ai,openai,automation
Classifier: Development Status :: 3 - Alpha
Classifier: Intended Audience :: Developers
Classifier: Intended Audience :: System Administrators
Classifier: License :: OSI Approved :: MIT License
Classifier: Operating System :: OS Independent
Classifier: Programming Language :: Python :: 3
Classifier: Programming Language :: Python :: 3.7
Classifier: Programming Language :: Python :: 3.8
Classifier: Programming Language :: Python :: 3.9
Classifier: Programming Language :: Python :: 3.10
Classifier: Programming Language :: Python :: 3.11
Classifier: Programming Language :: Python :: 3.12
Classifier: Topic :: System :: Shells
Classifier: Topic :: Terminals
Classifier: Topic :: Utilities
Classifier: Topic :: Scientific/Engineering :: Artificial Intelligence
Requires-Python: >=3.7
License-File: LICENSE
Requires-Dist: openai>=1.0.0
Dynamic: author
Dynamic: home-page
Dynamic: license-file
Dynamic: requires-python
